LICENSE
MANIFEST.in
README.rst
setup.py
django_qlik_tools.egg-info/PKG-INFO
django_qlik_tools.egg-info/SOURCES.txt
django_qlik_tools.egg-info/dependency_links.txt
django_qlik_tools.egg-info/not-zip-safe
django_qlik_tools.egg-info/top_level.txt
qlik_tools/__init__.py
qlik_tools/management/__init__.py
qlik_tools/management/commands/__init__.py
qlik_tools/management/commands/createextractionqvs.py